bootswatch/__init__.py
bootswatch/theme/cerulean/__init__.py
bootswatch/theme/cerulean/apps.py
bootswatch/theme/cerulean/auth_hooks.py
bootswatch/theme/cosmo/__init__.py
bootswatch/theme/cosmo/apps.py
bootswatch/theme/cosmo/auth_hooks.py
bootswatch/theme/cyborg/__init__.py
bootswatch/theme/cyborg/apps.py
bootswatch/theme/cyborg/auth_hooks.py
bootswatch/theme/journal/__init__.py
bootswatch/theme/journal/apps.py
bootswatch/theme/journal/auth_hooks.py
bootswatch/theme/litera/__init__.py
bootswatch/theme/litera/apps.py
bootswatch/theme/litera/auth_hooks.py
bootswatch/theme/lumen/__init__.py
bootswatch/theme/lumen/apps.py
bootswatch/theme/lumen/auth_hooks.py
bootswatch/theme/lux/__init__.py
bootswatch/theme/lux/apps.py
bootswatch/theme/lux/auth_hooks.py
bootswatch/theme/minty/__init__.py
bootswatch/theme/minty/apps.py
bootswatch/theme/minty/auth_hooks.py
bootswatch/theme/morph/__init__.py
bootswatch/theme/morph/apps.py
bootswatch/theme/morph/auth_hooks.py
bootswatch/theme/pulse/__init__.py
bootswatch/theme/pulse/apps.py
bootswatch/theme/pulse/auth_hooks.py
bootswatch/theme/quartz/__init__.py
bootswatch/theme/quartz/apps.py
bootswatch/theme/quartz/auth_hooks.py
bootswatch/theme/sandstone/__init__.py
bootswatch/theme/sandstone/apps.py
bootswatch/theme/sandstone/auth_hooks.py
bootswatch/theme/simplex/__init__.py
bootswatch/theme/simplex/apps.py
bootswatch/theme/simplex/auth_hooks.py
bootswatch/theme/sketchy/__init__.py
bootswatch/theme/sketchy/apps.py
bootswatch/theme/sketchy/auth_hooks.py
bootswatch/theme/slate/__init__.py
bootswatch/theme/slate/apps.py
bootswatch/theme/slate/auth_hooks.py
bootswatch/theme/solar/__init__.py
bootswatch/theme/solar/apps.py
bootswatch/theme/solar/auth_hooks.py
bootswatch/theme/spacelab/__init__.py
bootswatch/theme/spacelab/apps.py
bootswatch/theme/spacelab/auth_hooks.py
bootswatch/theme/superhero/__init__.py
bootswatch/theme/superhero/apps.py
bootswatch/theme/superhero/auth_hooks.py
bootswatch/theme/united/__init__.py
aa_bootswatch-0.2.0.dist-info/LICENSE
aa_bootswatch-0.2.0.dist-info/WHEEL
aa_bootswatch-0.2.0.dist-info/METADATA
aa_bootswatch-0.2.0.dist-info/RECORD
